django_msms_admin/__init__.py
django_msms_admin/admin.py
django_msms_admin/apps.py
django_msms_admin/models.py
django_msms_admin/tests.py
django_msms_admin/views.py
django_msms_admin/locale/zh_Hans/LC_MESSAGES/django.mo
django_msms_admin/locale/zh_Hans/LC_MESSAGES/django.po
django_msms_admin/migrations/__init__.py
django_msms_admin/static/django-msms-admin/css/django-msms-admin.css
django_msms_admin/static/django-msms-admin/js/django-msms-admin.js
django_msms_admin/templates/admin/select-subclass-model-view.html
django_msms_admin-0.2.2.dist-info/LICENSE
django_msms_admin-0.2.2.dist-info/METADATA
django_msms_admin-0.2.2.dist-info/WHEEL
django_msms_admin-0.2.2.dist-info/top_level.txt
django_msms_admin-0.2.2.dist-info/RECORD
