Metadata-Version: 2.1
Name: django-msms-admin
Version: 0.2.2
Summary: Intelligent management for multiple subclass models in django's admin site.
Author: Jiang Tao
Author-email: jiangtao@zencore.cn
Maintainer: Jiang Tao
Maintainer-email: jiangtao@zencore.cn
License: MIT
Keywords: django admin extentions,django msms admin
Classifier: Development Status :: 5 - Production/Stable
Classifier: Intended Audience :: Developers
Classifier: Topic :: Software Development :: Libraries :: Python Modules
Classifier: License :: OSI Approved :: MIT License
Classifier: Programming Language :: Python :: 3
Classifier: Programming Language :: Python :: 3 :: Only
License-File: LICENSE
Requires-Dist: django
Requires-Dist: django-simple-tags >=0.6.0
